banner_lsiwh37249/__init__.py
banner_lsiwh37249/banner.py
banner_lsiwh37249-0.5.0.dist-info/METADATA
banner_lsiwh37249-0.5.0.dist-info/WHEEL
banner_lsiwh37249-0.5.0.dist-info/entry_points.txt
banner_lsiwh37249-0.5.0.dist-info/top_level.txt
banner_lsiwh37249-0.5.0.dist-info/RECORD
