Metadata-Version: 2.1
Name: banner_lsiwh37249
Version: 0.5.0
Summary: Banner fun
Author-email: lsiwh37249 <lsiwh37249@gmail.com>
License: MIT
Project-URL: Homepage, https://github.com/lsiwh37249/banner_lsiwh37249
Project-URL: Issues, https://github.com/lsiwh37249/banner_lsiwh37249/issues
Requires-Python: >=3.9
Requires-Dist: pyfiglet >=1.0.2
